{
  "config": {
    "name": "oracle_rich",
    "seed": 0,
    "backbone_layers": null,
    "num_envs": 100,
    "env_steps_per_cycle": 2000,
    "steps_per_env": 200,
    "rotate_envs": true,
    "augment": true,
    "gradient_steps": 5000,
    "gradient_steps_per_cycle": 500,
    "learning_starts": 1000,
    "sequence_length": 256,
    "batch_size": 4,
    "lr": 1e-05,
    "exploration_mode": "oracle",
    "exploration_ends": 10000,
    "per_env_exploration_steps": 150,
    "epsilon_floor": 0.05,
    "gamma_step": 1.0,
    "gamma_episode": 0.99,
    "tau": 0.0005,
    "step_penalty": 0.0,
    "eval_maps": 10,
    "eval_steps": 150,
    "eval_fracs": [
      0.5,
      1.0
    ],
    "final_eval_temperatures": [
      0.0,
      0.2
    ]
  },
  "device": "cuda",
  "cycles": [
    {
      "env_steps": 2000,
      "episodes": 102,
      "mean_reward": 0.0784313753247261,
      "mean_length": 16.627450942993164,
      "distinct_envs_visited": 10,
      "grad_steps": 0,
      "train": {
        "loss_mean": 0.0016848558852516362,
        "loss_last": 3.53511750290636e-05,
        "q_mean": 0.12051524170627817,
        "grad_steps": 500
      }
    },
    {
      "env_steps": 4000,
      "episodes": 146,
      "mean_reward": 0.25342464447021484,
      "mean_length": 11.082191467285156,
      "distinct_envs_visited": 20,
      "grad_steps": 500,
      "train": {
        "loss_mean": 0.01232388601749699,
        "loss_last": 0.011902953498065472,
        "q_mean": 0.15606270621716975,
        "grad_steps": 1000
      }
    },
    {
      "env_steps": 6000,
      "episodes": 153,
      "mean_reward": 0.3660130798816681,
      "mean_length": 10.908496856689453,
      "distinct_envs_visited": 30,
      "grad_steps": 1000,
      "train": {
        "loss_mean": 0.01117065415142133,
        "loss_last": 0.00343868019990623,
        "q_mean": 0.14098458668589592,
        "grad_steps": 1500
      }
    },
    {
      "env_steps": 8000,
      "episodes": 111,
      "mean_reward": 0.2432432472705841,
      "mean_length": 14.981982231140137,
      "distinct_envs_visited": 40,
      "grad_steps": 1500,
      "train": {
        "loss_mean": 0.008529248404742248,
        "loss_last": 0.01178650837391615,
        "q_mean": 0.16380516201257705,
        "grad_steps": 2000
      }
    },
    {
      "env_steps": 10000,
      "episodes": 137,
      "mean_reward": 0.029197080060839653,
      "mean_length": 12.36496353149414,
      "distinct_envs_visited": 50,
      "grad_steps": 2000,
      "train": {
        "loss_mean": 0.007092618560192932,
        "loss_last": 0.007400707807391882,
        "q_mean": 0.16215980181097983,
        "grad_steps": 2500
      }
    },
    {
      "env_steps": 12000,
      "episodes": 142,
      "mean_reward": 0.18309858441352844,
      "mean_length": 12.042253494262695,
      "distinct_envs_visited": 60,
      "grad_steps": 2500,
      "train": {
        "loss_mean": 0.006930776501445507,
        "loss_last": 0.003921978175640106,
        "q_mean": 0.17049909983575345,
        "grad_steps": 3000
      }
    },
    {
      "env_steps": 14000,
      "episodes": 116,
      "mean_reward": 0.1034482792019844,
      "mean_length": 14.293103218078613,
      "distinct_envs_visited": 70,
      "grad_steps": 3000,
      "train": {
        "loss_mean": 0.005423101419553859,
        "loss_last": 0.005606064572930336,
        "q_mean": 0.1607935710698366,
        "grad_steps": 3500
      }
    },
    {
      "env_steps": 16000,
      "episodes": 150,
      "mean_reward": 0.07333333045244217,
      "mean_length": 11.073333740234375,
      "distinct_envs_visited": 80,
      "grad_steps": 3500,
      "train": {
        "loss_mean": 0.005581879664881853,
        "loss_last": 0.0033978153951466084,
        "q_mean": 0.1691600980013609,
        "grad_steps": 4000
      }
    },
    {
      "env_steps": 18000,
      "episodes": 138,
      "mean_reward": 0.21014492213726044,
      "mean_length": 11.956521987915039,
      "distinct_envs_visited": 90,
      "grad_steps": 4000,
      "train": {
        "loss_mean": 0.005807708018226549,
        "loss_last": 0.01631881669163704,
        "q_mean": 0.1847630788832903,
        "grad_steps": 4500
      }
    },
    {
      "env_steps": 20000,
      "episodes": 128,
      "mean_reward": 0.0,
      "mean_length": 12.7109375,
      "distinct_envs_visited": 100,
      "grad_steps": 4500,
      "train": {
        "loss_mean": 0.004916455126876826,
        "loss_last": 0.0010023739887401462,
        "q_mean": 0.17761907067894936,
        "grad_steps": 5000
      }
    }
  ],
  "evals": [
    {
      "holdout": true,
      "policy": "random",
      "temperature": 0.0,
      "episodes_total": 135,
      "success_rate": 0.08246753246753247,
      "first_half_success": 0.12833333333333333,
      "second_half_success": 0.041666666666666664,
      "mean_episode_length": 12.659642173615858,
      "bump_frac": 0.21816688180961807,
      "stuck_frac": 0.0,
      "per_env": [
        {
          "map_id": 1000000,
          "episodes": 28,
          "success_rate": 0.0,
          "first_episode_success": 0.0,
          "first_half_success": 0.0,
          "second_half_success": 0.0,
          "mean_length": 4.357142857142857,
          "bump_frac": 0.13829787234042554,
          "stuck_frac": 0.0
        },
        {
          "map_id": 1000001,
          "episodes": 14,
          "success_rate": 0.0,
          "first_episode_success": 0.0,
          "first_half_success": 0.0,
          "second_half_success": 0.0,
          "mean_length": 9.142857142857142,
          "bump_frac": 0.2066115702479339,
          "stuck_frac": 0.0
        },
        {
          "map_id": 1000002,
          "episodes": 7,
          "success_rate": 0.0,
          "first_episode_success": 0.0,
          "first_half_success": 0.0,
          "second_half_success": 0.0,
          "mean_length": 19.285714285714285,
          "bump_frac": 0.24444444444444444,
          "stuck_frac": 0.0
        },
        {
          "map_id": 1000003,
          "episodes": 25,
          "success_rate": 0.0,
          "first_episode_success": 0.0,
          "first_half_success": 0.0,
          "second_half_success": 0.0,
          "mean_length": 4.88,
          "bump_frac": 0.20202020202020202,
          "stuck_frac": 0.0
        },
        {
          "map_id": 1000004,
          "episodes": 7,
          "success_rate": 0.14285714285714285,
          "first_episode_success": 1.0,
          "first_half_success": 0.3333333333333333,
          "second_half_success": 0.0,
          "mean_length": 19.857142857142858,
          "bump_frac": 0.23703703703703705,
          "stuck_frac": 0.0
        },
        {
          "map_id": 1000005,
          "episodes": 8,
          "success_rate": 0.375,
          "first_episode_success": 0.0,
          "first_half_success": 0.5,
          "second_half_success": 0.25,
          "mean_length": 17.5,
          "bump_frac": 0.17293233082706766,
          "stuck_frac": 0.0
        },
        {
          "map_id": 1000006,
          "episodes": 11,
          "success_rate": 0.18181818181818182,
          "first_episode_success": 0.0,
          "first_half_success": 0.2,
          "second_half_success": 0.16666666666666666,
          "mean_length": 11.909090909090908,
          "bump_frac": 0.2755905511811024,
          "stuck_frac": 0.0
        },
        {
          "map_id": 1000007,
          "episodes": 19,
          "success_rate": 0.0,
          "first_episode_success": 0.0,
          "first_half_success": 0.0,
          "second_half_success": 0.0,
          "mean_length": 6.7894736842105265,
          "bump_frac": 0.35135135135135137,
          "stuck_frac": 0.0
        },
        {
          "map_id": 1000008,
          "episodes": 8,
          "success_rate": 0.125,
          "first_episode_success": 0.0,
          "first_half_success": 0.25,
          "second_half_success": 0.0,
          "mean_length": 16.125,
          "bump_frac": 0.23308270676691728,
          "stuck_frac": 0.0
        },
        {
          "map_id": 1000009,
          "episodes": 8,
          "success_rate": 0.0,
          "first_episode_success": 0.0,
          "first_half_success": 0.0,
          "second_half_success": 0.0,
          "mean_length": 16.75,
          "bump_frac": 0.12030075187969924,
          "stuck_frac": 0.0
        }
      ],
      "grad_steps": 0
    },
    {
      "holdout": true,
      "policy": "model",
      "temperature": 0.0,
      "episodes_total": 152,
      "success_rate": 0.01111111111111111,
      "first_half_success": 0.025,
      "second_half_success": 0.0,
      "mean_episode_length": 27.122573917310756,
      "bump_frac": 0.578952904397692,
      "stuck_frac": 0.13066666666666665,
      "per_env": [
        {
          "map_id": 1000000,
          "episodes": 57,
          "success_rate": 0.0,
          "first_episode_success": 0.0,
          "first_half_success": 0.0,
          "second_half_success": 0.0,
          "mean_length": 1.5614035087719298,
          "bump_frac": 0.6857142857142857,
          "stuck_frac": 0.0
        },
        {
          "map_id": 1000001,
          "episodes": 11,
          "success_rate": 0.0,
          "first_episode_success": 0.0,
          "first_half_success": 0.0,
          "second_half_success": 0.0,
          "mean_length": 11.818181818181818,
          "bump_frac": 0.6220472440944882,
          "stuck_frac": 0.18666666666666668
        },
        {
          "map_id": 1000002,
          "episodes": 39,
          "success_rate": 0.0,
          "first_episode_success": 0.0,
          "first_half_success": 0.0,
          "second_half_success": 0.0,
          "mean_length": 2.8461538461538463,
          "bump_frac": 0.05555555555555555,
          "stuck_frac": 0.0
        },
        {
          "map_id": 1000003,
          "episodes": 2,
          "success_rate": 0.0,
          "first_episode_success": 0.0,
          "first_half_success": 0.0,
          "second_half_success": 0.0,
          "mean_length": 50.0,
          "bump_frac": 0.6344827586206897,
          "stuck_frac": 0.0
        },
        {
          "map_id": 1000004,
          "episodes": 2,
          "success_rate": 0.0,
          "first_episode_success": 0.0,
          "first_half_success": 0.0,
          "second_half_success": 0.0,
          "mean_length": 50.0,
          "bump_frac": 0.696551724137931,
          "stuck_frac": 0.06666666666666667
        },
        {
          "map_id": 1000005,
          "episodes": 9,
          "success_rate": 0.1111111111111111,
          "first_episode_success": 1.0,
          "first_half_success": 0.25,
          "second_half_success": 0.0,
          "mean_length": 15.333333333333334,
          "bump_frac": 0.6717557251908397,
          "stuck_frac": 0.21333333333333335
        },
        {
          "map_id": 1000006,
          "episodes": 3,
          "success_rate": 0.0,
          "first_episode_success": 0.0,
          "first_half_success": 0.0,
          "second_half_success": 0.0,
          "mean_length": 34.666666666666664,
          "bump_frac": 0.9230769230769231,
          "stuck_frac": 0.62
        },
        {
          "map_id": 1000007,
          "episodes": 25,
          "success_rate": 0.0,
          "first_episode_success": 0.0,
          "first_half_success": 0.0,
          "second_half_success": 0.0,
          "mean_length": 5.0,
          "bump_frac": 0.19,
          "stuck_frac": 0.0
        },
        {
          "map_id": 1000008,
          "episodes": 2,
          "success_rate": 0.0,
          "first_episode_success": 0.0,
          "first_half_success": 0.0,
          "second_half_success": 0.0,
          "mean_length": 50.0,
          "bump_frac": 0.5655172413793104,
          "stuck_frac": 0.0
        },
        {
          "map_id": 1000009,
          "episodes": 2,
          "success_rate": 0.0,
          "first_episode_success": 0.0,
          "first_half_success": 0.0,
          "second_half_success": 0.0,
          "mean_length": 50.0,
          "bump_frac": 0.7448275862068966,
          "stuck_frac": 0.22
        }
      ],
      "grad_steps": 2500
    },
    {
      "holdout": false,
      "policy": "model",
      "temperature": 0.0,
      "episodes_total": 260,
      "success_rate": 0.016666666666666666,
      "first_half_success": 0.020833333333333332,
      "second_half_success": 0.0125,
      "mean_episode_length": 12.559024960467584,
      "bump_frac": 0.526194921065364,
      "stuck_frac": 0.11000000000000001,
      "per_env": [
        {
          "map_id": 0,
          "episodes": 50,
          "success_rate": 0.0,
          "first_episode_success": 0.0,
          "first_half_success": 0.0,
          "second_half_success": 0.0,
          "mean_length": 2.0,
          "bump_frac": 0.4,
          "stuck_frac": 0.0
        },
        {
          "map_id": 1,
          "episodes": 16,
          "success_rate": 0.125,
          "first_episode_success": 0.0,
          "first_half_success": 0.125,
          "second_half_success": 0.125,
          "mean_length": 8.125,
          "bump_frac": 0.17094017094017094,
          "stuck_frac": 0.03333333333333333
        },
        {
          "map_id": 2,
          "episodes": 2,
          "success_rate": 0.0,
          "first_episode_success": 0.0,
          "first_half_success": 0.0,
          "second_half_success": 0.0,
          "mean_length": 50.0,
          "bump_frac": 0.4068965517241379,
          "stuck_frac": 0.0
        },
        {
          "map_id": 3,
          "episodes": 25,
          "success_rate": 0.0,
          "first_episode_success": 0.0,
          "first_half_success": 0.0,
          "second_half_success": 0.0,
          "mean_length": 4.92,
          "bump_frac": 0.6262626262626263,
          "stuck_frac": 0.10666666666666667
        },
        {
          "map_id": 4,
          "episodes": 24,
          "success_rate": 0.041666666666666664,
          "first_episode_success": 0.0,
          "first_half_success": 0.08333333333333333,
          "second_half_success": 0.0,
          "mean_length": 5.25,
          "bump_frac": 0.47058823529411764,
          "stuck_frac": 0.26
        },
        {
          "map_id": 5,
          "episodes": 4,
          "success_rate": 0.0,
          "first_episode_success": 0.0,
          "first_half_success": 0.0,
          "second_half_success": 0.0,
          "mean_length": 30.25,
          "bump_frac": 0.8085106382978723,
          "stuck_frac": 0.32666666666666666
        },
        {
          "map_id": 6,
          "episodes": 9,
          "success_rate": 0.0,
          "first_episode_success": 0.0,
          "first_half_success": 0.0,
          "second_half_success": 0.0,
          "mean_length": 15.222222222222221,
          "bump_frac": 0.7862595419847328,
          "stuck_frac": 0.20666666666666667
        },
        {
          "map_id": 7,
          "episodes": 61,
          "success_rate": 0.0,
          "first_episode_success": 0.0,
          "first_half_success": 0.0,
          "second_half_success": 0.0,
          "mean_length": 1.459016393442623,
          "bump_frac": 0.42857142857142855,
          "stuck_frac": 0.0
        },
        {
          "map_id": 8,
          "episodes": 13,
          "success_rate": 0.0,
          "first_episode_success": 0.0,
          "first_half_success": 0.0,
          "second_half_success": 0.0,
          "mean_length": 6.846153846153846,
          "bump_frac": 0.6504065040650406,
          "stuck_frac": 0.15333333333333332
        },
        {
          "map_id": 9,
          "episodes": 56,
          "success_rate": 0.0,
          "first_episode_success": 0.0,
          "first_half_success": 0.0,
          "second_half_success": 0.0,
          "mean_length": 1.5178571428571428,
          "bump_frac": 0.5135135135135135,
          "stuck_frac": 0.013333333333333334
        }
      ],
      "grad_steps": 2500
    },
    {
      "holdout": true,
      "policy": "model",
      "temperature": 0.0,
      "episodes_total": 177,
      "success_rate": 0.1,
      "first_half_success": 0.1,
      "second_half_success": 0.1,
      "mean_episode_length": 17.869453003994458,
      "bump_frac": 0.635070893519389,
      "stuck_frac": 0.27799999999999997,
      "per_env": [
        {
          "map_id": 1000000,
          "episodes": 47,
          "success_rate": 0.0,
          "first_episode_success": 0.0,
          "first_half_success": 0.0,
          "second_half_success": 0.0,
          "mean_length": 2.148936170212766,
          "bump_frac": 0.8545454545454545,
          "stuck_frac": 0.05333333333333334
        },
        {
          "map_id": 1000001,
          "episodes": 9,
          "success_rate": 0.0,
          "first_episode_success": 0.0,
          "first_half_success": 0.0,
          "second_half_success": 0.0,
          "mean_length": 10.222222222222221,
          "bump_frac": 0.7175572519083969,
          "stuck_frac": 0.4066666666666667
        },
        {
          "map_id": 1000002,
          "episodes": 27,
          "success_rate": 0.0,
          "first_episode_success": 0.0,
          "first_half_success": 0.0,
          "second_half_success": 0.0,
          "mean_length": 4.333333333333333,
          "bump_frac": 0.5578947368421052,
          "stuck_frac": 0.08
        },
        {
          "map_id": 1000003,
          "episodes": 3,
          "success_rate": 0.0,
          "first_episode_success": 0.0,
          "first_half_success": 0.0,
          "second_half_success": 0.0,
          "mean_length": 37.666666666666664,
          "bump_frac": 0.8601398601398601,
          "stuck_frac": 0.5333333333333333
        },
        {
          "map_id": 1000004,
          "episodes": 3,
          "success_rate": 0.0,
          "first_episode_success": 0.0,
          "first_half_success": 0.0,
          "second_half_success": 0.0,
          "mean_length": 35.666666666666664,
          "bump_frac": 0.8391608391608392,
          "stuck_frac": 0.35333333333333333
        },
        {
          "map_id": 1000005,
          "episodes": 8,
          "success_rate": 0.0,
          "first_episode_success": 0.0,
          "first_half_success": 0.0,
          "second_half_success": 0.0,
          "mean_length": 13.0,
          "bump_frac": 0.7142857142857143,
          "stuck_frac": 0.36666666666666664
        },
        {
          "map_id": 1000006,
          "episodes": 29,
          "success_rate": 1.0,
          "first_episode_success": 1.0,
          "first_half_success": 1.0,
          "second_half_success": 1.0,
          "mean_length": 4.0344827586206895,
          "bump_frac": 0.01098901098901099,
          "stuck_frac": 0.0
        },
        {
          "map_id": 1000007,
          "episodes": 45,
          "success_rate": 0.0,
          "first_episode_success": 0.0,
          "first_half_success": 0.0,
          "second_half_success": 0.0,
          "mean_length": 2.2888888888888888,
          "bump_frac": 0.03389830508474576,
          "stuck_frac": 0.0
        },
        {
          "map_id": 1000008,
          "episodes": 3,
          "success_rate": 0.0,
          "first_episode_success": 0.0,
          "first_half_success": 0.0,
          "second_half_success": 0.0,
          "mean_length": 35.333333333333336,
          "bump_frac": 0.8951048951048951,
          "stuck_frac": 0.44666666666666666
        },
        {
          "map_id": 1000009,
          "episodes": 3,
          "success_rate": 0.0,
          "first_episode_success": 0.0,
          "first_half_success": 0.0,
          "second_half_success": 0.0,
          "mean_length": 34.0,
          "bump_frac": 0.8671328671328671,
          "stuck_frac": 0.54
        }
      ],
      "grad_steps": 5000
    },
    {
      "holdout": true,
      "policy": "model",
      "temperature": 0.2,
      "episodes_total": 163,
      "success_rate": 0.10666666666666666,
      "first_half_success": 0.06999999999999999,
      "second_half_success": 0.14250000000000002,
      "mean_episode_length": 11.160063025210084,
      "bump_frac": 0.21032346025278592,
      "stuck_frac": 0.0,
      "per_env": [
        {
          "map_id": 1000000,
          "episodes": 28,
          "success_rate": 0.0,
          "first_episode_success": 0.0,
          "first_half_success": 0.0,
          "second_half_success": 0.0,
          "mean_length": 4.178571428571429,
          "bump_frac": 0.15053763440860216,
          "stuck_frac": 0.0
        },
        {
          "map_id": 1000001,
          "episodes": 17,
          "success_rate": 0.0,
          "first_episode_success": 0.0,
          "first_half_success": 0.0,
          "second_half_success": 0.0,
          "mean_length": 7.647058823529412,
          "bump_frac": 0.22608695652173913,
          "stuck_frac": 0.0
        },
        {
          "map_id": 1000002,
          "episodes": 7,
          "success_rate": 0.0,
          "first_episode_success": 0.0,
          "first_half_success": 0.0,
          "second_half_success": 0.0,
          "mean_length": 19.285714285714285,
          "bump_frac": 0.22962962962962963,
          "stuck_frac": 0.0
        },
        {
          "map_id": 1000003,
          "episodes": 16,
          "success_rate": 0.0,
          "first_episode_success": 0.0,
          "first_half_success": 0.0,
          "second_half_success": 0.0,
          "mean_length": 8.125,
          "bump_frac": 0.1794871794871795,
          "stuck_frac": 0.0
        },
        {
          "map_id": 1000004,
          "episodes": 30,
          "success_rate": 0.6666666666666666,
          "first_episode_success": 0.0,
          "first_half_success": 0.5333333333333333,
          "second_half_success": 0.8,
          "mean_length": 3.933333333333333,
          "bump_frac": 0.20224719101123595,
          "stuck_frac": 0.0
        },
        {
          "map_id": 1000005,
          "episodes": 12,
          "success_rate": 0.3333333333333333,
          "first_episode_success": 0.0,
          "first_half_success": 0.16666666666666666,
          "second_half_success": 0.5,
          "mean_length": 11.416666666666666,
          "bump_frac": 0.128,
          "stuck_frac": 0.0
        },
        {
          "map_id": 1000006,
          "episodes": 14,
          "success_rate": 0.0,
          "first_episode_success": 0.0,
          "first_half_success": 0.0,
          "second_half_success": 0.0,
          "mean_length": 9.214285714285714,
          "bump_frac": 0.24793388429752067,
          "stuck_frac": 0.0
        },
        {
          "map_id": 1000007,
          "episodes": 20,
          "success_rate": 0.0,
          "first_episode_success": 0.0,
          "first_half_success": 0.0,
          "second_half_success": 0.0,
          "mean_length": 6.5,
          "bump_frac": 0.35454545454545455,
          "stuck_frac": 0.0
        },
        {
          "map_id": 1000008,
          "episodes": 4,
          "success_rate": 0.0,
          "first_episode_success": 0.0,
          "first_half_success": 0.0,
          "second_half_success": 0.0,
          "mean_length": 32.5,
          "bump_frac": 0.19148936170212766,
          "stuck_frac": 0.0
        },
        {
          "map_id": 1000009,
          "episodes": 15,
          "success_rate": 0.06666666666666667,
          "first_episode_success": 0.0,
          "first_half_success": 0.0,
          "second_half_success": 0.125,
          "mean_length": 8.8,
          "bump_frac": 0.19327731092436976,
          "stuck_frac": 0.0
        }
      ],
      "grad_steps": 5000
    },
    {
      "holdout": false,
      "policy": "model",
      "temperature": 0.0,
      "episodes_total": 215,
      "success_rate": 0.22972136222910217,
      "first_half_success": 0.1736111111111111,
      "second_half_success": 0.27999999999999997,
      "mean_episode_length": 11.341430176612384,
      "bump_frac": 0.3614082335560889,
      "stuck_frac": 0.10533333333333335,
      "per_env": [
        {
          "map_id": 0,
          "episodes": 17,
          "success_rate": 0.8235294117647058,
          "first_episode_success": 0.0,
          "first_half_success": 0.625,
          "second_half_success": 1.0,
          "mean_length": 7.823529411764706,
          "bump_frac": 0.04310344827586207,
          "stuck_frac": 0.0
        },
        {
          "map_id": 1,
          "episodes": 19,
          "success_rate": 0.47368421052631576,
          "first_episode_success": 0.0,
          "first_half_success": 0.1111111111111111,
          "second_half_success": 0.8,
          "mean_length": 6.842105263157895,
          "bump_frac": 0.08108108108108109,
          "stuck_frac": 0.0
        },
        {
          "map_id": 2,
          "episodes": 3,
          "success_rate": 0.0,
          "first_episode_success": 0.0,
          "first_half_success": 0.0,
          "second_half_success": 0.0,
          "mean_length": 41.666666666666664,
          "bump_frac": 0.5314685314685315,
          "stuck_frac": 0.2
        },
        {
          "map_id": 3,
          "episodes": 6,
          "success_rate": 0.0,
          "first_episode_success": 0.0,
          "first_half_success": 0.0,
          "second_half_success": 0.0,
          "mean_length": 20.0,
          "bump_frac": 0.7956204379562044,
          "stuck_frac": 0.4866666666666667
        },
        {
          "map_id": 4,
          "episodes": 37,
          "success_rate": 0.0,
          "first_episode_success": 0.0,
          "first_half_success": 0.0,
          "second_half_success": 0.0,
          "mean_length": 3.054054054054054,
          "bump_frac": 0.013157894736842105,
          "stuck_frac": 0.0
        },
        {
          "map_id": 5,
          "episodes": 29,
          "success_rate": 1.0,
          "first_episode_success": 1.0,
          "first_half_success": 1.0,
          "second_half_success": 1.0,
          "mean_length": 4.0344827586206895,
          "bump_frac": 0.01098901098901099,
          "stuck_frac": 0.0
        },
        {
          "map_id": 6,
          "episodes": 20,
          "success_rate": 0.0,
          "first_episode_success": 0.0,
          "first_half_success": 0.0,
          "second_half_success": 0.0,
          "mean_length": 6.2,
          "bump_frac": 0.30275229357798167,
          "stuck_frac": 0.0
        },
        {
          "map_id": 7,
          "episodes": 53,
          "success_rate": 0.0,
          "first_episode_success": 0.0,
          "first_half_success": 0.0,
          "second_half_success": 0.0,
          "mean_length": 1.8113207547169812,
          "bump_frac": 0.9069767441860465,
          "stuck_frac": 0.0
        },
        {
          "map_id": 8,
          "episodes": 7,
          "success_rate": 0.0,
          "first_episode_success": 0.0,
          "first_half_success": 0.0,
          "second_half_success": 0.0,
          "mean_length": 16.857142857142858,
          "bump_frac": 0.7111111111111111,
          "stuck_frac": 0.3333333333333333
        },
        {
          "map_id": 9,
          "episodes": 24,
          "success_rate": 0.0,
          "first_episode_success": 0.0,
          "first_half_success": 0.0,
          "second_half_success": 0.0,
          "mean_length": 5.125,
          "bump_frac": 0.21782178217821782,
          "stuck_frac": 0.03333333333333333
        }
      ],
      "grad_steps": 5000
    }
  ],
  "timing": {
    "total_s": 1569.2109515666962,
    "rollout_s": 1.5433506965637207,
    "train_s": 1370.1844608783722,
    "eval_s": 192.30354475975037
  }
}